{
  "anka": {
    "support": {
      "contact": [
        {
          "qrcode": "qrcodeImg",
          "icon": "wechat"
        },
        {
          "link": {
            "href": "https://zhuanlan.zhihu.com/ricequant",
            "newBlock": true
          },
          "icon": "zhihu"
        },
        {
          "link": {
            "href": "https://xueqiu.com/u/ricequant",
            "newBlock": true
          },
          "icon": "xueqiu"
        },
        {
          "link": {
            "href": "https://weibo.com/ricequant",
            "newBlock": true
          },
          "icon": "weibo"
        },
        {
          "link": {
            "href": "https://github.com/ricequant",
            "newBlock": true
          },
          "icon": "github"
        }
      ],
      "info": [
        {
          "value": "public@ricequant.com",
          "label": "联系邮箱"
        },
        {
          "value": "0755-22676337",
          "label": "客服电话"
        },
        {
          "value": "3010840691",
          "label": "QQ"
        },
        {
          "value": "9:00 - 18:00",
          "label": "周一至周五"
        }
      ],
      "label": "支持"
    },
    "header": {
      "others": [
        {
          "link": "/recruitment/social",
          "label": "社会招聘"
        },
        {
          "link": "/recruitment/school",
          "label": "校园招聘"
        },
        {
          "link": "/about",
          "label": "关于我们"
        }
      ],
      "default": [
        {
          "links": [
            {
              "link": "/rqdata",
              "icon": "rqdata",
              "label": "RQData（金融数据API）"
            },

            {
              "link": "/rqpro",
              "icon": "rqpro",
              "label": "RQPro（投研交易）"
            },
            {
              "link": "/ams",
              "icon": "rqams",
              "label": "RQAMS（资产管理系统）"
            },
            {
              "link": "/rqoptimizer",
              "icon": "rqoptimizer",
              "label": "RQOptimizer ( 组合优化器 )"
            }
          ],
          "more": true,
          "label": "产品"
        },
        {
          "link": "/pricing",
          "label": "定价"
        },
        {
          "more": true,
          "label": "支持",
          "links": [
            {
              "link": {
                "href": "/doc/rqdata-institutional#research-version",
                "outer": true
              },
              "label": "RQData使用文档"
            },
            {
              "link": "/pricing#rqpro",
              "label": "RQPro试用咨询"
            },
            {
              "link": {
                "href": "/doc/api/python/chn",
                "outer": true
              },
              "label": "量化平台使用文档"
            },
            {
              "link": {
                "href": "/site/courses",
                "outer": true
              },
              "label": "米筐量化学院"
            }
          ]
        },
        {
          "link": "/edu",
          "label": "教育专区"
        },
        {
          "link": "/quant",
          "label": "量化平台"
        },
        {
          "more": true,
          "label": "量化社区",
          "links": [
            {
              "link": {
                "href": "/community",
                "outer": true,
                "newBlock": true
              },
              "label": "量化社区"
            },
            {
              "link": {
                "href": "/site/tournaments",
                "outer": true
              },
              "label": "量化大赛"
            },
            {
              "link": {
                "href": "/site/scrafts",
                "outer": true
              },
              "label": "策略英雄榜"
            }
          ]
        },
        {
          "more": true,
          "label": "加入我们",
          "links": [
            {
              "link": {
                "href": "/recruitment/social",
                "inner": true,
                "newBlock": true
              },
              "label": "社会招聘"
            },
            {
              "link": {
                "href": "/recruitment/school",
                "inner": true,
                "newBlock": true
              },
              "label": "校园招聘"
            }
          ]
        }
      ]
    }
  },
  "logged": {
    "right": [
      {
        "link": {
          "href": "/welcome/trial/road-show"
        },
        "className": "road-show",
        "label": "预约路演"
      },
      {
        "links": [
          {
            "link": {
              "href": "/doc/rqdata-institutional#research-version",
              "newBlock": true
            },
            "label": "RQData使用文档"
          },
          {
            "link": {
              "href": "/doc/api/python/chn",
              "newBlock": true
            },
            "label": "量化平台文档"
          },
          {
            "link": {
              "href": "/doc/rqams",
              "newBlock": true
            },
            "label": "RQAMS使用文档"
          }
        ],
        "label": "帮助文档"
      },
      {
        "link": {
          "href": "/community",
          "newBlock": true
        },
        "label": "社区"
      },
      {
        "type": "theme"
      },
      {
        "links": [
          {
            "link": "/dashboard/profile",
            "label": "个人主页"
          },
          {
            "link": "/dashboard/account#setting",
            "label": "账号中心"
          },
          {
            "link": "/",
            "label": "回到首页"
          },
          {
            "event": "logout",
            "label": "登出账号"
          }
        ],
        "img": "avator",
        "type": "avatar"
      }
    ],
    "left": [
      {
        "link": "/quant/",
        "label": "量化"
      },
      {
        "link": "/ams/",
        "label": "AMS"
      }
    ]
  }
}
